{"documents":[{"id":1,"documentType":{"id":1,"name":"Паспорт"},"series":"4004","number":"523134","dateOfIssue":"2023-05-18T21:00:00.000Z","isArchive":false,"isMain":true},{"id":2,"documentType":{"id":2,"name":"Загран. паспорт"},"series":"4005","number":"523135","dateOfIssue":"2023-05-18T21:00:00.000Z","isArchive":false,"isMain":false},{"id":3,"documentType":{"id":3,"name":"Св-во о рождении"},"series":"4006","number":"523136","dateOfIssue":"2023-05-18T21:00:00.000Z","isArchive":false,"isMain":false},{"id":4,"documentType":{"id":1,"name":"Паспорт"},"series":"4007","number":"523137","dateOfIssue":"2023-05-18T21:00:00.000Z","isArchive":true,"isMain":false},{"documentType":{"id":1,"name":"Паспорт"},"series":"4004","number":"523134","organization":{"id":1,"name":"ГУ МВД Первого района"},"dateOfIssue":"2023-05-18T21:00:00.000Z","divisionCode":"123-223","isArchive":false,"isMain":true}],"documentTypes":[{"id":1,"name":"Паспорт"},{"id":2,"name":"Загран. паспорт"},{"id":3,"name":"Св-во о рождении"}],"organizations":[{"id":1,"name":"ГУ МВД Первого района"},{"id":2,"name":"ГУ МВД Второго района"},{"id":1,"name":"ГУ МВД Третьего района"}]}